tvm_multi_scan_exporter/__init__.py
tvm_multi_scan_exporter/aggregated_scan_exporter.py
tvm_multi_scan_exporter/configuration.py
tvm_multi_scan_exporter/constants.py
tvm_multi_scan_exporter/database.py
tvm_multi_scan_exporter/deduplicator.py
tvm_multi_scan_exporter/duck_db.py
tvm_multi_scan_exporter/files.py
tvm_multi_scan_exporter/models.py
tvm_multi_scan_exporter/scan_exporter.py
tvm_multi_scan_exporter/scan_fetcher.py
tvm_multi_scan_exporter/scan_transformer.py
tvm_multi_scan_exporter/util.py
tvm_multi_scan_exporter-0.1.1.dist-info/licenses/LICENSE
tvm_multi_scan_exporter-0.1.1.dist-info/METADATA
tvm_multi_scan_exporter-0.1.1.dist-info/WHEEL
tvm_multi_scan_exporter-0.1.1.dist-info/top_level.txt
tvm_multi_scan_exporter-0.1.1.dist-info/RECORD
