Metadata-Version: 2.4
Name: tvm_multi_scan_exporter
Version: 0.1.1
Summary: A Python library to aggregate Scan Exports into a single export
Author: Tenable, Inc.
Author-email: Exports Team <exports-integration@tenable.com>
License-Expression: MIT
Project-URL: Homepage, https://github.com/tenable/tvm_multi_scan_exporter/blob/main/README.md
Project-URL: Bug Tracker, https://github.com/tenable/tvm_multi_scan_exporter/issues
Keywords: tenable,tenable vulnerability management
Classifier: Development Status :: 5 - Production/Stable
Classifier: Intended Audience :: Developers
Classifier: Topic :: Software Development
Classifier: Topic :: Software Development :: Libraries
Classifier: Topic :: Software Development :: Libraries :: Application Frameworks
Classifier: Programming Language :: Python :: 3.11
Classifier: Programming Language :: Python :: 3.12
Classifier: Programming Language :: Python :: 3.13
Requires-Python: >=3.10
License-File: LICENSE
Requires-Dist: pytenable==1.7.4
Requires-Dist: duckdb==1.2.1
Requires-Dist: SQLAlchemy==2.0.39
Requires-Dist: pyodbc==5.2.0
Requires-Dist: pyarrow==19.0.1
Requires-Dist: pandas==2.2.3
Requires-Dist: tomli==2.2.1
Requires-Dist: future>=0.18.3
Requires-Dist: certifi>=2024.7.4
Requires-Dist: idna>=3.7
Requires-Dist: jinja2>=3.1.6
Requires-Dist: pillow>=10.3.0
Requires-Dist: pygments>=2.15.0
Requires-Dist: setuptools>=78.1.1
Requires-Dist: marshmallow<4.0.0
Provides-Extra: dev
Requires-Dist: pytest==8.3.5; extra == "dev"
Dynamic: license-file
